setup.py
copr_gui/__init__.py
copr_gui.egg-info/PKG-INFO
copr_gui.egg-info/SOURCES.txt
copr_gui.egg-info/dependency_links.txt
copr_gui.egg-info/requires.txt
copr_gui.egg-info/top_level.txt
copr_gui/__dynamic/builds_monitor.py
copr_gui/__dynamic/launcher.py
copr_gui/__dynamic/monitor.py
copr_gui/__dynamic/monitor_helper.py
copr_gui/__dynamic/packages_monitor.py
copr_gui/__dynamic/project_chroots_monitor.py
copr_gui/__dynamic/projects_monitor.py
copr_gui/__dynamic/settings.py
copr_gui/static/build_settings.py
copr_gui/static/cached_store.py
copr_gui/static/copr_api.py
copr_gui/static/new_build_settings.py
copr_gui/static/old_build_settings.py
copr_gui/static/package_settings.py
copr_gui/static/project_chroot_settings.py
copr_gui/static/project_settings.py
copr_gui/static/source_type_settings.py
copr_gui/static/spec_types.py
tests/test_cached_store.py